{
  "resourceType" : "ValueSet",
  "id" : "2f5e18df-1837-40bd-9a9c-e2096b0572d0-167",
  "url" : "http://hl7.org/fhir/comparison/ValueSet/2f5e18df-1837-40bd-9a9c-e2096b0572d0-167",
  "name" : "UnionServiceDeliveryLocationRoleTypeAndFRCoreValueSetLocationType",
  "title" : "Union of ServiceDeliveryLocationRoleType And FR Core ValueSet Location type",
  "status" : "active",
  "date" : "2024-04-03T14:07:11+00:00",
  "jurisdiction" : [{
    "coding" : [{
      "system" : "urn:iso:std:iso:3166",
      "code" : "FR",
      "display" : "France"
    }]
  }],
  "compose" : {
    "include" : [{
      "filter" : [{
        "property" : "concept",
        "op" : "descendent-of",
        "value" : "_ServiceDeliveryLocationRoleType"
      }]
    }]
  }
}